python_rocket_league-0.0.3.dist-info/METADATA
python_rocket_league-0.0.3.dist-info/RECORD
python_rocket_league-0.0.3.dist-info/WHEEL
python_rocket_league-0.0.3.dist-info/top_level.txt
rlapi/__init__.py
rlapi/client.py
rlapi/constants.py
rlapi/test_client.py
